agd/Domain.py
agd/FiniteDifferences.py
agd/Interpolation.py
agd/License.txt
agd/LinearPDE.py
agd/LinearParallel.py
agd/Plotting.py
agd/Selling.py
agd/Sphere.py
agd/__init__.py
agd/AutomaticDifferentiation/Base.py
agd/AutomaticDifferentiation/Dense.py
agd/AutomaticDifferentiation/Dense2.py
agd/AutomaticDifferentiation/Optimization.py
agd/AutomaticDifferentiation/Reverse.py
agd/AutomaticDifferentiation/Reverse2.py
agd/AutomaticDifferentiation/Sparse.py
agd/AutomaticDifferentiation/Sparse2.py
agd/AutomaticDifferentiation/__init__.py
agd/AutomaticDifferentiation/ad_generic.py
agd/AutomaticDifferentiation/ad_specific.py
agd/AutomaticDifferentiation/cupy_generic.py
agd/AutomaticDifferentiation/cupy_support.py
agd/AutomaticDifferentiation/functional.py
agd/AutomaticDifferentiation/misc.py
agd/AutomaticDifferentiation/AD_CUDA/__init__.py
agd/AutomaticDifferentiation/AD_CUDA/simplify_ad.py
agd/AutomaticDifferentiation/AD_CUDA/cuda/simplify_ad.h
agd/Eikonal/DictIn.py
agd/Eikonal/DictIn_detail.py
agd/Eikonal/FileIO.py
agd/Eikonal/LibraryCall.py
agd/Eikonal/__init__.py
agd/Eikonal/run_detail.py
agd/Eikonal/HFM_CUDA/AnisotropicWave.py
agd/Eikonal/HFM_CUDA/BeckmanOT.py
agd/Eikonal/HFM_CUDA/Eigh.py
agd/Eikonal/HFM_CUDA/MinCut.py
agd/Eikonal/HFM_CUDA/ProjectionTTI.py
agd/Eikonal/HFM_CUDA/SellingAnisotropicDiffusion.py
agd/Eikonal/HFM_CUDA/ShapeFromShading.py
agd/Eikonal/HFM_CUDA/VoronoiDecomposition.py
agd/Eikonal/HFM_CUDA/_GetGeodesics.py
agd/Eikonal/HFM_CUDA/_Interface.py
agd/Eikonal/HFM_CUDA/_Kernel.py
agd/Eikonal/HFM_CUDA/_PostProcess.py
agd/Eikonal/HFM_CUDA/_SetArgs.py
agd/Eikonal/HFM_CUDA/_SetGeometry.py
agd/Eikonal/HFM_CUDA/_StopCriterion.py
agd/Eikonal/HFM_CUDA/__init__.py
agd/Eikonal/HFM_CUDA/_solvers.py
agd/Eikonal/HFM_CUDA/cupy_module_helper.py
agd/Eikonal/HFM_CUDA/graph_reverse.py
agd/Eikonal/HFM_CUDA/inf_convolution.py
agd/Eikonal/HFM_CUDA/kernel_traits.py
agd/Eikonal/HFM_CUDA/misc.py
agd/Eikonal/HFM_CUDA/cuda/AsymmetricQuadratic_.h
agd-0.2.15.dist-info/METADATA
agd-0.2.15.dist-info/WHEEL
agd-0.2.15.dist-info/top_level.txt
agd-0.2.15.dist-info/RECORD
